matontools/__init__.py
matontools/__main__.py
matontools/main.py
matontools-0.0.7.dist-info/METADATA
matontools-0.0.7.dist-info/WHEEL
matontools-0.0.7.dist-info/top_level.txt
matontools-0.0.7.dist-info/RECORD
