Metadata-Version: 2.1
Name: matontools
Version: 0.0.7
Summary: A set of functions to speed up Data Science workflows
Home-page: https://github.com/NathanMaton/matontools
Author: Nathan Maton
Author-email: nathanmaton@gmail.com
License: MIT
Platform: UNKNOWN
Classifier: License :: OSI Approved :: MIT License
Classifier: Programming Language :: Python :: 3
Classifier: Programming Language :: Python :: 3.7
Requires-Dist: pandas
Requires-Dist: numpy
